Metadata-Version: 1.0
Name: FWapi
Version: 0.1
Summary: Simple Python API for filmweb.pl
Home-page: https://github.com/ajbrzoz/FWapi
Author: Anna Brzozowska
Author-email: brzozowskaanna5@gmail.com
License: UNKNOWN
Platform: UNKNOWN
